todo_list.py
todo_list-0.0.3.dist-info/top_level.txt
todo_list-0.0.3.dist-info/entry_points.txt
todo_list-0.0.3.dist-info/METADATA
todo_list-0.0.3.dist-info/RECORD
todo_list-0.0.3.dist-info/DESCRIPTION.rst
todo_list-0.0.3.dist-info/metadata.json
todo_list-0.0.3.dist-info/WHEEL
